flask_ipfs/__init__.py
flask_ipfs/base.py
flask_ipfs/fission.py
flask_ipfs/http.py
flask_ipfs/infura.py
flask_ipfs/test.py
Flask_IPFS-0.1.0b5.dist-info/LICENSE
Flask_IPFS-0.1.0b5.dist-info/METADATA
Flask_IPFS-0.1.0b5.dist-info/WHEEL
Flask_IPFS-0.1.0b5.dist-info/top_level.txt
Flask_IPFS-0.1.0b5.dist-info/RECORD
