Metadata-Version: 2.1
Name: Flask-IPFS
Version: 0.1.0b5
Summary: IPFS Plugin for Flask
Home-page: https://github.com/zatoichi-labs/Flask-IPFS
Author: Zatoichi Labs
Author-email: admin@zatoichilabs.com
License: MIT
Platform: any
Classifier: Environment :: Web Environment
Classifier: Intended Audience :: Developers
Classifier: License :: OSI Approved :: MIT License
Classifier: Operating System :: OS Independent
Classifier: Programming Language :: Python
Classifier: Topic :: Internet :: WWW/HTTP :: Dynamic Content
Classifier: Topic :: Software Development :: Libraries :: Python Modules
Requires-Dist: Flask
Requires-Dist: ipfshttpclient
Requires-Dist: multiaddr
Requires-Dist: py-cid
Provides-Extra: dev
Requires-Dist: bumpversion ; extra == 'dev'
Requires-Dist: ipython ; extra == 'dev'
Requires-Dist: pytest ; extra == 'dev'
Requires-Dist: twine ; extra == 'dev'
